Metadata-Version: 2.1
Name: scikit-physlearn
Version: 0.1.7
Summary: A machine learning library for regression.
Home-page: https://github.com/a-wozniakowski/scikit-physlearn
Maintainer: Alex Wozniakowski
Maintainer-email: wozn0001@e.ntu.edu.sg
License: MIT
Download-URL: https://github.com/a-wozniakowski/scikit-physlearn
Project-URL: Paper, https://arxiv.org/abs/2005.06194
Platform: UNKNOWN
Classifier: Intended Audience :: Science/Research
Classifier: Intended Audience :: Developers
Classifier: Programming Language :: Python
Classifier: Topic :: Software Development
Classifier: Topic :: Scientific/Engineering :: Artificial Intelligence
Classifier: Operating System :: Microsoft :: Windows
Classifier: Operating System :: POSIX
Classifier: Operating System :: Unix
Classifier: Operating System :: MacOS
Classifier: Programming Language :: Python :: 3.6
Classifier: Programming Language :: Python :: 3.7
Classifier: Programming Language :: Python :: 3.8
License-File: LICENSE
Requires-Dist: matplotlib (<=3.2.0)
Requires-Dist: numpy
Requires-Dist: scipy
Requires-Dist: scikit-learn (>=0.24.1)
Requires-Dist: pandas (>=1.0.0)
Requires-Dist: shap (>=0.36.0)
Requires-Dist: ipython (>=7.11.0)
Requires-Dist: bayesian-optimization (>=1.2.0)
Requires-Dist: catboost (>=0.23.2)
Requires-Dist: xgboost (>=1.4.1)
Requires-Dist: lightgbm (>=2.3.0)
Requires-Dist: mlxtend (>=0.17.0)
Requires-Dist: python-levenshtein-wheels (>=0.13.1)
Provides-Extra: docs
Requires-Dist: sphinx (>=3.0.3) ; extra == 'docs'
Requires-Dist: sphinx-gallery (>=0.7.0) ; extra == 'docs'
